{
	"graduale": "graduale",
	"antiphona": "antiphonale",
	"sequentiar": "sequentiar",
	"psalterium": "psalterium",
	"Hymnar": "hymnar",
	"prozessionale": "prozessionale",
	"responsoriale": "responsoriale",
	"orgelbuch": "orgelbuch",
	"lamentatio": "lamentationen",
	"manuale": "manuale",
	"litaneien": "litaneien",
	"gesänge": "gesaenge",
	"choral": "coralbuch",
	"intonation": "intonationsbuch",
	"temporale": "temporale",
	"teil": "temporale",
	"diurnale": "temporale",
	"nocturnale": "temporale",
	"osterzeit": "temporale"
}
